letsplay/__init__.py
letsplay/finders.py
letsplay/main.py
letsplay/mpris.py
letsplay/output.py
letsplay/player.py
letsplay/song.py
letsplay/utils.py
letsplay-0.1.1.data/scripts/letsplay
letsplay-0.1.1.dist-info/DESCRIPTION.rst
letsplay-0.1.1.dist-info/METADATA
letsplay-0.1.1.dist-info/RECORD
letsplay-0.1.1.dist-info/WHEEL
letsplay-0.1.1.dist-info/metadata.json
letsplay-0.1.1.dist-info/top_level.txt
letsplay-0.1.1.dist-info/zip-safe
