Metadata-Version: 2.0
Name: letsplay
Version: 0.1.1
Summary: Extensible music player library for Python
Home-page: http://github.com/marcinn/letsplay
Author: Marcin Nowak
Author-email: marcin.j.nowak@gmail.com
License: GPL3
Platform: UNKNOWN
Requires-Dist: pytaglib
Requires-Dist: observable
Requires-Dist: mplayer.py
Requires-Dist: pygobject
Requires-Dist: dbus-python
